imagecompression4/__init__.py
imagecompression4/helpers.py
imagecompression4/image_compression.py
imagecompression4/matrix_operations.py
imagecompression4/reis_algorithm.py
imagecompression4-0.1.4.dist-info/LICENSE.txt
imagecompression4-0.1.4.dist-info/METADATA
imagecompression4-0.1.4.dist-info/WHEEL
imagecompression4-0.1.4.dist-info/top_level.txt
imagecompression4-0.1.4.dist-info/RECORD
